{"name":"rbxmath","className":"Folder","filePaths":["default.project.json"],"children":[{"name":"FastFourierTransform","className":"ModuleScript","filePaths":["src/Packages\\FastFourierTransform.lua"]},{"name":"Graphs","className":"ModuleScript","filePaths":["src/Packages\\Graphs.lua"]},{"name":"Interpolation","className":"ModuleScript","filePaths":["src/Packages\\Interpolation.lua"]},{"name":"Matrices","className":"ModuleScript","filePaths":["src/Packages\\Matrices.lua"]},{"name":"Noise","className":"ModuleScript","filePaths":["src/Packages\\Noise.lua"]},{"name":"NumericalMethods","className":"ModuleScript","filePaths":["src/Packages\\NumericalMethods.lua"]},{"name":"Ode","className":"ModuleScript","filePaths":["src/Packages\\Ode.lua"]},{"name":"PrimeList","className":"ModuleScript","filePaths":["src/Packages\\PrimeList.lua"]},{"name":"Primes","className":"ModuleScript","filePaths":["src/Packages\\Primes.lua"]},{"name":"Scalars","className":"ModuleScript","filePaths":["src/Packages\\Scalars.lua"]},{"name":"Sets","className":"ModuleScript","filePaths":["src/Packages\\Sets.lua"]},{"name":"Spline","className":"ModuleScript","filePaths":["src/Packages\\Spline.lua"]},{"name":"Tools","className":"ModuleScript","filePaths":["src/Packages\\Tools.lua"]},{"name":"_Index","className":"Folder","children":[{"name":"ukendio_fast-fourier-transform@0.1.0","className":"Folder","children":[{"name":"Primes","className":"ModuleScript","filePaths":["src/Packages\\_Index\\ukendio_fast-fourier-transform@0.1.0\\Primes.lua"]},{"name":"Scalars","className":"ModuleScript","filePaths":["src/Packages\\_Index\\ukendio_fast-fourier-transform@0.1.0\\Scalars.lua"]},{"name":"Tools","className":"ModuleScript","filePaths":["src/Packages\\_Index\\ukendio_fast-fourier-transform@0.1.0\\Tools.lua"]},{"name":"fast-fourier-transform","className":"Folder","filePaths":["src/Packages\\_Index\\ukendio_fast-fourier-transform@0.1.0\\fast-fourier-transform\\default.project.json"],"children":[{"name":"FastFourierTransform","className":"ModuleScript","filePaths":["src/Packages\\_Index\\ukendio_fast-fourier-transform@0.1.0\\fast-fourier-transform\\src\\FastFourierTransform.lua"]}]}]},{"name":"ukendio_graphs@0.1.0","className":"Folder","children":[{"name":"Matrices","className":"ModuleScript","filePaths":["src/Packages\\_Index\\ukendio_graphs@0.1.0\\Matrices.lua"]},{"name":"Sets","className":"ModuleScript","filePaths":["src/Packages\\_Index\\ukendio_graphs@0.1.0\\Sets.lua"]},{"name":"Tools","className":"ModuleScript","filePaths":["src/Packages\\_Index\\ukendio_graphs@0.1.0\\Tools.lua"]},{"name":"graphs","className":"ModuleScript","filePaths":["src/Packages\\_Index\\ukendio_graphs@0.1.0\\graphs\\src\\init.lua","src/Packages\\_Index\\ukendio_graphs@0.1.0\\graphs\\default.project.json"]}]},{"name":"ukendio_interpolation@0.1.0","className":"Folder","children":[{"name":"FastFourierTransform","className":"ModuleScript","filePaths":["src/Packages\\_Index\\ukendio_interpolation@0.1.0\\FastFourierTransform.lua"]},{"name":"Matrices","className":"ModuleScript","filePaths":["src/Packages\\_Index\\ukendio_interpolation@0.1.0\\Matrices.lua"]},{"name":"Primes","className":"ModuleScript","filePaths":["src/Packages\\_Index\\ukendio_interpolation@0.1.0\\Primes.lua"]},{"name":"Scalars","className":"ModuleScript","filePaths":["src/Packages\\_Index\\ukendio_interpolation@0.1.0\\Scalars.lua"]},{"name":"Tools","className":"ModuleScript","filePaths":["src/Packages\\_Index\\ukendio_interpolation@0.1.0\\Tools.lua"]},{"name":"interpolation","className":"ModuleScript","filePaths":["src/Packages\\_Index\\ukendio_interpolation@0.1.0\\interpolation\\src\\init.lua","src/Packages\\_Index\\ukendio_interpolation@0.1.0\\interpolation\\default.project.json"]}]},{"name":"ukendio_matrices@0.1.2","className":"Folder","children":[{"name":"Scalars","className":"ModuleScript","filePaths":["src/Packages\\_Index\\ukendio_matrices@0.1.2\\Scalars.lua"]},{"name":"Tools","className":"ModuleScript","filePaths":["src/Packages\\_Index\\ukendio_matrices@0.1.2\\Tools.lua"]},{"name":"matrices","className":"ModuleScript","filePaths":["src/Packages\\_Index\\ukendio_matrices@0.1.2\\matrices\\src\\init.lua","src/Packages\\_Index\\ukendio_matrices@0.1.2\\matrices\\default.project.json"]}]},{"name":"ukendio_noise@0.1.1","className":"Folder","children":[{"name":"noise","className":"ModuleScript","filePaths":["src/Packages\\_Index\\ukendio_noise@0.1.1\\noise\\src\\init.lua","src/Packages\\_Index\\ukendio_noise@0.1.1\\noise\\default.project.json"]}]},{"name":"ukendio_numerical-methods@0.1.0","className":"Folder","children":[{"name":"Matrices","className":"ModuleScript","filePaths":["src/Packages\\_Index\\ukendio_numerical-methods@0.1.0\\Matrices.lua"]},{"name":"Tools","className":"ModuleScript","filePaths":["src/Packages\\_Index\\ukendio_numerical-methods@0.1.0\\Tools.lua"]},{"name":"numerical-methods","className":"ModuleScript","filePaths":["src/Packages\\_Index\\ukendio_numerical-methods@0.1.0\\numerical-methods\\src\\init.lua","src/Packages\\_Index\\ukendio_numerical-methods@0.1.0\\numerical-methods\\default.project.json"]}]},{"name":"ukendio_ode@0.1.0","className":"Folder","children":[{"name":"interpolation","className":"ModuleScript","filePaths":["src/Packages\\_Index\\ukendio_ode@0.1.0\\interpolation.lua"]},{"name":"matrices","className":"ModuleScript","filePaths":["src/Packages\\_Index\\ukendio_ode@0.1.0\\matrices.lua"]},{"name":"ode","className":"ModuleScript","filePaths":["src/Packages\\_Index\\ukendio_ode@0.1.0\\ode\\src\\init.lua","src/Packages\\_Index\\ukendio_ode@0.1.0\\ode\\default.project.json"]},{"name":"tools","className":"ModuleScript","filePaths":["src/Packages\\_Index\\ukendio_ode@0.1.0\\tools.lua"]}]},{"name":"ukendio_primelist@0.1.2","className":"Folder","children":[{"name":"primelist","className":"ModuleScript","filePaths":["src/Packages\\_Index\\ukendio_primelist@0.1.2\\primelist\\src\\init.lua","src/Packages\\_Index\\ukendio_primelist@0.1.2\\primelist\\default.project.json"]}]},{"name":"ukendio_primes@0.1.0","className":"Folder","children":[{"name":"PrimeList","className":"ModuleScript","filePaths":["src/Packages\\_Index\\ukendio_primes@0.1.0\\PrimeList.lua"]},{"name":"primes","className":"ModuleScript","filePaths":["src/Packages\\_Index\\ukendio_primes@0.1.0\\primes\\src\\init.lua","src/Packages\\_Index\\ukendio_primes@0.1.0\\primes\\default.project.json"]}]},{"name":"ukendio_scalars@0.1.0","className":"Folder","children":[{"name":"Tools","className":"ModuleScript","filePaths":["src/Packages\\_Index\\ukendio_scalars@0.1.0\\Tools.lua"]},{"name":"scalars","className":"ModuleScript","filePaths":["src/Packages\\_Index\\ukendio_scalars@0.1.0\\scalars\\src\\init.lua","src/Packages\\_Index\\ukendio_scalars@0.1.0\\scalars\\default.project.json"]}]},{"name":"ukendio_sets@0.1.0","className":"Folder","children":[{"name":"Tools","className":"ModuleScript","filePaths":["src/Packages\\_Index\\ukendio_sets@0.1.0\\Tools.lua"]},{"name":"sets","className":"Folder","filePaths":["src/Packages\\_Index\\ukendio_sets@0.1.0\\sets\\default.project.json"],"children":[{"name":"Sets","className":"ModuleScript","filePaths":["src/Packages\\_Index\\ukendio_sets@0.1.0\\sets\\src\\Sets.lua"]}]}]},{"name":"ukendio_spline@0.1.1","className":"Folder","children":[{"name":"FastFourierTransform","className":"ModuleScript","filePaths":["src/Packages\\_Index\\ukendio_spline@0.1.1\\FastFourierTransform.lua"]},{"name":"Interpolation","className":"ModuleScript","filePaths":["src/Packages\\_Index\\ukendio_spline@0.1.1\\Interpolation.lua"]},{"name":"Matrices","className":"ModuleScript","filePaths":["src/Packages\\_Index\\ukendio_spline@0.1.1\\Matrices.lua"]},{"name":"PrimeList","className":"ModuleScript","filePaths":["src/Packages\\_Index\\ukendio_spline@0.1.1\\PrimeList.lua"]},{"name":"Primes","className":"ModuleScript","filePaths":["src/Packages\\_Index\\ukendio_spline@0.1.1\\Primes.lua"]},{"name":"Scalars","className":"ModuleScript","filePaths":["src/Packages\\_Index\\ukendio_spline@0.1.1\\Scalars.lua"]},{"name":"Tools","className":"ModuleScript","filePaths":["src/Packages\\_Index\\ukendio_spline@0.1.1\\Tools.lua"]},{"name":"spline","className":"ModuleScript","filePaths":["src/Packages\\_Index\\ukendio_spline@0.1.1\\spline\\src\\init.lua","src/Packages\\_Index\\ukendio_spline@0.1.1\\spline\\default.project.json"],"children":[{"name":"SplineUtils","className":"ModuleScript","filePaths":["src/Packages\\_Index\\ukendio_spline@0.1.1\\spline\\src\\SplineUtils.lua"]},{"name":"Splines","className":"Folder","children":[{"name":"CatmullRom","className":"ModuleScript","filePaths":["src/Packages\\_Index\\ukendio_spline@0.1.1\\spline\\src\\Splines\\CatmullRom.lua"]},{"name":"CubicBezier","className":"ModuleScript","filePaths":["src/Packages\\_Index\\ukendio_spline@0.1.1\\spline\\src\\Splines\\CubicBezier.lua"]},{"name":"CubicHermite","className":"ModuleScript","filePaths":["src/Packages\\_Index\\ukendio_spline@0.1.1\\spline\\src\\Splines\\CubicHermite.lua"]},{"name":"CubicPolynomial","className":"ModuleScript","filePaths":["src/Packages\\_Index\\ukendio_spline@0.1.1\\spline\\src\\Splines\\CubicPolynomial.lua"]},{"name":"Linear","className":"ModuleScript","filePaths":["src/Packages\\_Index\\ukendio_spline@0.1.1\\spline\\src\\Splines\\Linear.lua"]},{"name":"Position","className":"ModuleScript","filePaths":["src/Packages\\_Index\\ukendio_spline@0.1.1\\spline\\src\\Splines\\Position.lua"]},{"name":"QuadraticBezier","className":"ModuleScript","filePaths":["src/Packages\\_Index\\ukendio_spline@0.1.1\\spline\\src\\Splines\\QuadraticBezier.lua"]},{"name":"QuadraticPolynomial","className":"ModuleScript","filePaths":["src/Packages\\_Index\\ukendio_spline@0.1.1\\spline\\src\\Splines\\QuadraticPolynomial.lua"]}]},{"name":"Types","className":"ModuleScript","filePaths":["src/Packages\\_Index\\ukendio_spline@0.1.1\\spline\\src\\Types.lua"]}]}]},{"name":"ukendio_tools@0.1.0","className":"Folder","children":[{"name":"tools","className":"ModuleScript","filePaths":["src/Packages\\_Index\\ukendio_tools@0.1.0\\tools\\src\\init.lua","src/Packages\\_Index\\ukendio_tools@0.1.0\\tools\\default.project.json"]}]}]}]}